{
    "key": "group_64ca9a5531411",
    "title": "Blocks",
    "fields": [
        {
            "key": "field_64ca9a550cf94",
            "label": "Blocks",
            "name": "blocks",
            "aria-label": "",
            "type": "flexible_content",
            "instructions": "",
            "required": 0,
            "conditional_logic": 0,
            "wrapper": {
                "width": "",
                "class": "",
                "id": ""
            },
            "layouts": {
                "layout_64ca9a6d95852": {
                    "key": "layout_64ca9a6d95852",
                    "name": "hero",
                    "label": "Hero",
                    "display": "block",
                    "sub_fields": [
                        {
                            "key": "field_64ca9aa70cf97",
                            "label": "Content",
                            "name": "",
                            "aria-label": "",
                            "type": "tab",
                            "instructions": "",
                            "required": 0,
                            "conditional_logic": 0,
                            "wrapper": {
                                "width": "",
                                "class": "",
                                "id": ""
                            },
                            "placement": "top",
                            "endpoint": 0
                        },
                        {
                            "key": "field_64ca9bab0cf9c",
                            "label": "Pre Title",
                            "name": "pre_title",
                            "aria-label": "",
                            "type": "text",
                            "instructions": "",
                            "required": 0,
                            "conditional_logic": 0,
                            "wrapper": {
                                "width": "",
                                "class": "",
                                "id": ""
                            },
                            "default_value": "",
                            "maxlength": "",
                            "placeholder": "",
                            "prepend": "",
                            "append": ""
                        },
                        {
                            "key": "field_64ca9bbf0cf9d",
                            "label": "Title",
                            "name": "title",
                            "aria-label": "",
                            "type": "text",
                            "instructions": "Wrap the text that you want to be colored like this : <span>Growth<\/span>.",
                            "required": 1,
                            "conditional_logic": 0,
                            "wrapper": {
                                "width": "",
                                "class": "",
                                "id": ""
                            },
                            "default_value": "",
                            "maxlength": "",
                            "placeholder": "",
                            "prepend": "",
                            "append": ""
                        },
                        {
                            "key": "field_64ca9bca0cf9e",
                            "label": "Button",
                            "name": "button",
                            "aria-label": "",
                            "type": "link",
                            "instructions": "",
                            "required": 0,
                            "conditional_logic": 0,
                            "wrapper": {
                                "width": "",
                                "class": "",
                                "id": ""
                            },
                            "return_format": "array"
                        },
                        {
                            "key": "field_64ca9bdc0cf9f",
                            "label": "Background Image",
                            "name": "background_image",
                            "aria-label": "",
                            "type": "image",
                            "instructions": "",
                            "required": 0,
                            "conditional_logic": 0,
                            "wrapper": {
                                "width": "",
                                "class": "",
                                "id": ""
                            },
                            "return_format": "id",
                            "library": "all",
                            "min_width": "",
                            "min_height": "",
                            "min_size": "",
                            "max_width": "",
                            "max_height": "",
                            "max_size": "",
                            "mime_types": "",
                            "preview_size": "medium"
                        },
                        {
                            "key": "field_64ca9ac70cf98",
                            "label": "Settings",
                            "name": "",
                            "aria-label": "",
                            "type": "tab",
                            "instructions": "",
                            "required": 0,
                            "conditional_logic": 0,
                            "wrapper": {
                                "width": "",
                                "class": "",
                                "id": ""
                            },
                            "placement": "top",
                            "endpoint": 0
                        },
                        {
                            "key": "field_64ca9ad20cf99",
                            "label": "Section Classes",
                            "name": "section_classes",
                            "aria-label": "",
                            "type": "text",
                            "instructions": "Space separated section classes.",
                            "required": 0,
                            "conditional_logic": 0,
                            "wrapper": {
                                "width": "",
                                "class": "",
                                "id": ""
                            },
                            "default_value": "",
                            "maxlength": "",
                            "placeholder": "",
                            "prepend": "",
                            "append": ""
                        },
                        {
                            "key": "field_64ca9b730cf9a",
                            "label": "Section ID",
                            "name": "section_id",
                            "aria-label": "",
                            "type": "text",
                            "instructions": "",
                            "required": 0,
                            "conditional_logic": 0,
                            "wrapper": {
                                "width": "",
                                "class": "",
                                "id": ""
                            },
                            "default_value": "",
                            "maxlength": "",
                            "placeholder": "",
                            "prepend": "",
                            "append": ""
                        }
                    ],
                    "min": "",
                    "max": ""
                },
                "layout_64cb81098287c": {
                    "key": "layout_64cb81098287c",
                    "name": "featured_work",
                    "label": "Featured Work",
                    "display": "block",
                    "sub_fields": [
                        {
                            "key": "field_64cb81098287d",
                            "label": "Content",
                            "name": "",
                            "aria-label": "",
                            "type": "tab",
                            "instructions": "",
                            "required": 0,
                            "conditional_logic": 0,
                            "wrapper": {
                                "width": "",
                                "class": "",
                                "id": ""
                            },
                            "placement": "top",
                            "endpoint": 0
                        },
                        {
                            "key": "field_64cb81098287e",
                            "label": "Image",
                            "name": "image",
                            "aria-label": "",
                            "type": "image",
                            "instructions": "",
                            "required": 0,
                            "conditional_logic": 0,
                            "wrapper": {
                                "width": "",
                                "class": "",
                                "id": ""
                            },
                            "return_format": "id",
                            "library": "all",
                            "min_width": "",
                            "min_height": "",
                            "min_size": "",
                            "max_width": "",
                            "max_height": "",
                            "max_size": "",
                            "mime_types": "",
                            "preview_size": "medium"
                        },
                        {
                            "key": "field_64cb81098287f",
                            "label": "Pre Title",
                            "name": "pre_title",
                            "aria-label": "",
                            "type": "text",
                            "instructions": "",
                            "required": 0,
                            "conditional_logic": 0,
                            "wrapper": {
                                "width": "",
                                "class": "",
                                "id": ""
                            },
                            "default_value": "",
                            "maxlength": "",
                            "placeholder": "",
                            "prepend": "",
                            "append": ""
                        },
                        {
                            "key": "field_64cb810982880",
                            "label": "Title",
                            "name": "title",
                            "aria-label": "",
                            "type": "text",
                            "instructions": "",
                            "required": 1,
                            "conditional_logic": 0,
                            "wrapper": {
                                "width": "",
                                "class": "",
                                "id": ""
                            },
                            "default_value": "",
                            "maxlength": "",
                            "placeholder": "",
                            "prepend": "",
                            "append": ""
                        },
                        {
                            "key": "field_64cb814482886",
                            "label": "Description",
                            "name": "description",
                            "aria-label": "",
                            "type": "textarea",
                            "instructions": "",
                            "required": 0,
                            "conditional_logic": 0,
                            "wrapper": {
                                "width": "",
                                "class": "",
                                "id": ""
                            },
                            "default_value": "",
                            "maxlength": "",
                            "rows": 4,
                            "placeholder": "",
                            "new_lines": "br"
                        },
                        {
                            "key": "field_64cb817282887",
                            "label": "List items",
                            "name": "list_items",
                            "aria-label": "",
                            "type": "repeater",
                            "instructions": "",
                            "required": 0,
                            "conditional_logic": 0,
                            "wrapper": {
                                "width": "",
                                "class": "",
                                "id": ""
                            },
                            "layout": "block",
                            "min": 0,
                            "max": 0,
                            "collapsed": "field_64cb818282888",
                            "button_label": "Add List Item",
                            "rows_per_page": 20,
                            "sub_fields": [
                                {
                                    "key": "field_64cb818282888",
                                    "label": "List Text",
                                    "name": "list_text",
                                    "aria-label": "",
                                    "type": "text",
                                    "instructions": "",
                                    "required": 1,
                                    "conditional_logic": 0,
                                    "wrapper": {
                                        "width": "",
                                        "class": "",
                                        "id": ""
                                    },
                                    "default_value": "",
                                    "maxlength": "",
                                    "placeholder": "",
                                    "prepend": "",
                                    "append": "",
                                    "parent_repeater": "field_64cb817282887"
                                }
                            ]
                        },
                        {
                            "key": "field_64cb810982883",
                            "label": "Settings",
                            "name": "",
                            "aria-label": "",
                            "type": "tab",
                            "instructions": "",
                            "required": 0,
                            "conditional_logic": 0,
                            "wrapper": {
                                "width": "",
                                "class": "",
                                "id": ""
                            },
                            "placement": "top",
                            "endpoint": 0
                        },
                        {
                            "key": "field_64cb810982884",
                            "label": "Section Classes",
                            "name": "section_classes",
                            "aria-label": "",
                            "type": "text",
                            "instructions": "Space separated section classes.",
                            "required": 0,
                            "conditional_logic": 0,
                            "wrapper": {
                                "width": "",
                                "class": "",
                                "id": ""
                            },
                            "default_value": "",
                            "maxlength": "",
                            "placeholder": "",
                            "prepend": "",
                            "append": ""
                        },
                        {
                            "key": "field_64cb810982885",
                            "label": "Section ID",
                            "name": "section_id",
                            "aria-label": "",
                            "type": "text",
                            "instructions": "",
                            "required": 0,
                            "conditional_logic": 0,
                            "wrapper": {
                                "width": "",
                                "class": "",
                                "id": ""
                            },
                            "default_value": "",
                            "maxlength": "",
                            "placeholder": "",
                            "prepend": "",
                            "append": ""
                        }
                    ],
                    "min": "",
                    "max": ""
                },
                "layout_64cb84a405dbd": {
                    "key": "layout_64cb84a405dbd",
                    "name": "icons_slider",
                    "label": "Icons Slider",
                    "display": "block",
                    "sub_fields": [
                        {
                            "key": "field_64cb84a405dbe",
                            "label": "Content",
                            "name": "",
                            "aria-label": "",
                            "type": "tab",
                            "instructions": "",
                            "required": 0,
                            "conditional_logic": 0,
                            "wrapper": {
                                "width": "",
                                "class": "",
                                "id": ""
                            },
                            "placement": "top",
                            "endpoint": 0
                        },
                        {
                            "key": "field_64cb84a505dc3",
                            "label": "Icons",
                            "name": "icons",
                            "aria-label": "",
                            "type": "repeater",
                            "instructions": "",
                            "required": 0,
                            "conditional_logic": 0,
                            "wrapper": {
                                "width": "",
                                "class": "",
                                "id": ""
                            },
                            "layout": "block",
                            "min": 0,
                            "max": 0,
                            "collapsed": "field_64cb818282888",
                            "button_label": "Add Icon",
                            "rows_per_page": 20,
                            "sub_fields": [
                                {
                                    "key": "field_64cb84a505dc4",
                                    "label": "Icon",
                                    "name": "icon",
                                    "aria-label": "",
                                    "type": "image",
                                    "instructions": "",
                                    "required": 1,
                                    "conditional_logic": 0,
                                    "wrapper": {
                                        "width": "",
                                        "class": "",
                                        "id": ""
                                    },
                                    "return_format": "id",
                                    "library": "all",
                                    "min_width": "",
                                    "min_height": "",
                                    "min_size": "",
                                    "max_width": "",
                                    "max_height": "",
                                    "max_size": "",
                                    "mime_types": "",
                                    "preview_size": "medium",
                                    "parent_repeater": "field_64cb84a505dc3"
                                }
                            ]
                        },
                        {
                            "key": "field_64cb84a505dc5",
                            "label": "Settings",
                            "name": "",
                            "aria-label": "",
                            "type": "tab",
                            "instructions": "",
                            "required": 0,
                            "conditional_logic": 0,
                            "wrapper": {
                                "width": "",
                                "class": "",
                                "id": ""
                            },
                            "placement": "top",
                            "endpoint": 0
                        },
                        {
                            "key": "field_64cb84a505dc6",
                            "label": "Section Classes",
                            "name": "section_classes",
                            "aria-label": "",
                            "type": "text",
                            "instructions": "Space separated section classes.",
                            "required": 0,
                            "conditional_logic": 0,
                            "wrapper": {
                                "width": "",
                                "class": "",
                                "id": ""
                            },
                            "default_value": "",
                            "maxlength": "",
                            "placeholder": "",
                            "prepend": "",
                            "append": ""
                        },
                        {
                            "key": "field_64cb84a505dc7",
                            "label": "Section ID",
                            "name": "section_id",
                            "aria-label": "",
                            "type": "text",
                            "instructions": "",
                            "required": 0,
                            "conditional_logic": 0,
                            "wrapper": {
                                "width": "",
                                "class": "",
                                "id": ""
                            },
                            "default_value": "",
                            "maxlength": "",
                            "placeholder": "",
                            "prepend": "",
                            "append": ""
                        }
                    ],
                    "min": "",
                    "max": ""
                },
                "layout_64cb86da3ceb1": {
                    "key": "layout_64cb86da3ceb1",
                    "name": "three_columns_content",
                    "label": "Three Columns Content",
                    "display": "block",
                    "sub_fields": [
                        {
                            "key": "field_64cb86da3ceb2",
                            "label": "Content",
                            "name": "",
                            "aria-label": "",
                            "type": "tab",
                            "instructions": "",
                            "required": 0,
                            "conditional_logic": 0,
                            "wrapper": {
                                "width": "",
                                "class": "",
                                "id": ""
                            },
                            "placement": "top",
                            "endpoint": 0
                        },
                        {
                            "key": "field_64cb86eb3ceb8",
                            "label": "Title",
                            "name": "title",
                            "aria-label": "",
                            "type": "text",
                            "instructions": "",
                            "required": 0,
                            "conditional_logic": 0,
                            "wrapper": {
                                "width": "",
                                "class": "",
                                "id": ""
                            },
                            "default_value": "",
                            "maxlength": "",
                            "placeholder": "",
                            "prepend": "",
                            "append": ""
                        },
                        {
                            "key": "field_64cb86da3ceb3",
                            "label": "Content",
                            "name": "content",
                            "aria-label": "",
                            "type": "repeater",
                            "instructions": "",
                            "required": 0,
                            "conditional_logic": 0,
                            "wrapper": {
                                "width": "",
                                "class": "",
                                "id": ""
                            },
                            "layout": "block",
                            "min": 1,
                            "max": 0,
                            "collapsed": "field_64cb818282888",
                            "button_label": "Add Content",
                            "rows_per_page": 20,
                            "sub_fields": [
                                {
                                    "key": "field_64cb878f3ceba",
                                    "label": "Column 1",
                                    "name": "",
                                    "aria-label": "",
                                    "type": "tab",
                                    "instructions": "",
                                    "required": 0,
                                    "conditional_logic": 0,
                                    "wrapper": {
                                        "width": "",
                                        "class": "",
                                        "id": ""
                                    },
                                    "placement": "top",
                                    "endpoint": 0,
                                    "parent_repeater": "field_64cb86da3ceb3"
                                },
                                {
                                    "key": "field_64cb87a23cebb",
                                    "label": "Title",
                                    "name": "col_title_1",
                                    "aria-label": "",
                                    "type": "text",
                                    "instructions": "",
                                    "required": 1,
                                    "conditional_logic": 0,
                                    "wrapper": {
                                        "width": "",
                                        "class": "",
                                        "id": ""
                                    },
                                    "default_value": "",
                                    "maxlength": "",
                                    "placeholder": "",
                                    "prepend": "",
                                    "append": "",
                                    "parent_repeater": "field_64cb86da3ceb3"
                                },
                                {
                                    "key": "field_64cb87c73cebd",
                                    "label": "Column 2",
                                    "name": "",
                                    "aria-label": "",
                                    "type": "tab",
                                    "instructions": "",
                                    "required": 0,
                                    "conditional_logic": 0,
                                    "wrapper": {
                                        "width": "",
                                        "class": "",
                                        "id": ""
                                    },
                                    "placement": "top",
                                    "endpoint": 0,
                                    "parent_repeater": "field_64cb86da3ceb3"
                                },
                                {
                                    "key": "field_64cb87f7c0048",
                                    "label": "Title",
                                    "name": "col_title_2",
                                    "aria-label": "",
                                    "type": "link",
                                    "instructions": "",
                                    "required": 1,
                                    "conditional_logic": 0,
                                    "wrapper": {
                                        "width": "",
                                        "class": "",
                                        "id": ""
                                    },
                                    "return_format": "array",
                                    "parent_repeater": "field_64cb86da3ceb3"
                                },
                                {
                                    "key": "field_64cb880ec0049",
                                    "label": "Content",
                                    "name": "col_content_2",
                                    "aria-label": "",
                                    "type": "textarea",
                                    "instructions": "",
                                    "required": 0,
                                    "conditional_logic": 0,
                                    "wrapper": {
                                        "width": "",
                                        "class": "",
                                        "id": ""
                                    },
                                    "default_value": "",
                                    "maxlength": "",
                                    "rows": 4,
                                    "placeholder": "",
                                    "new_lines": "br",
                                    "parent_repeater": "field_64cb86da3ceb3"
                                },
                                {
                                    "key": "field_64cb87d6c0047",
                                    "label": "Column 3",
                                    "name": "",
                                    "aria-label": "",
                                    "type": "tab",
                                    "instructions": "",
                                    "required": 0,
                                    "conditional_logic": 0,
                                    "wrapper": {
                                        "width": "",
                                        "class": "",
                                        "id": ""
                                    },
                                    "placement": "top",
                                    "endpoint": 0,
                                    "parent_repeater": "field_64cb86da3ceb3"
                                },
                                {
                                    "key": "field_64cb882ec004a",
                                    "label": "Title",
                                    "name": "col_title_3",
                                    "aria-label": "",
                                    "type": "link",
                                    "instructions": "",
                                    "required": 1,
                                    "conditional_logic": 0,
                                    "wrapper": {
                                        "width": "",
                                        "class": "",
                                        "id": ""
                                    },
                                    "return_format": "array",
                                    "parent_repeater": "field_64cb86da3ceb3"
                                },
                                {
                                    "key": "field_64cb8832c004b",
                                    "label": "Content",
                                    "name": "col_content_3",
                                    "aria-label": "",
                                    "type": "textarea",
                                    "instructions": "",
                                    "required": 0,
                                    "conditional_logic": 0,
                                    "wrapper": {
                                        "width": "",
                                        "class": "",
                                        "id": ""
                                    },
                                    "default_value": "",
                                    "maxlength": "",
                                    "rows": 4,
                                    "placeholder": "",
                                    "new_lines": "br",
                                    "parent_repeater": "field_64cb86da3ceb3"
                                }
                            ]
                        },
                        {
                            "key": "field_64cb86da3ceb5",
                            "label": "Settings",
                            "name": "",
                            "aria-label": "",
                            "type": "tab",
                            "instructions": "",
                            "required": 0,
                            "conditional_logic": 0,
                            "wrapper": {
                                "width": "",
                                "class": "",
                                "id": ""
                            },
                            "placement": "top",
                            "endpoint": 0
                        },
                        {
                            "key": "field_64cb86da3ceb6",
                            "label": "Section Classes",
                            "name": "section_classes",
                            "aria-label": "",
                            "type": "text",
                            "instructions": "Space separated section classes.",
                            "required": 0,
                            "conditional_logic": 0,
                            "wrapper": {
                                "width": "",
                                "class": "",
                                "id": ""
                            },
                            "default_value": "",
                            "maxlength": "",
                            "placeholder": "",
                            "prepend": "",
                            "append": ""
                        },
                        {
                            "key": "field_64cb86da3ceb7",
                            "label": "Section ID",
                            "name": "section_id",
                            "aria-label": "",
                            "type": "text",
                            "instructions": "",
                            "required": 0,
                            "conditional_logic": 0,
                            "wrapper": {
                                "width": "",
                                "class": "",
                                "id": ""
                            },
                            "default_value": "",
                            "maxlength": "",
                            "placeholder": "",
                            "prepend": "",
                            "append": ""
                        }
                    ],
                    "min": "",
                    "max": ""
                },
                "layout_64cb8b45e5fbe": {
                    "key": "layout_64cb8b45e5fbe",
                    "name": "recent_projects",
                    "label": "Recent Projects",
                    "display": "block",
                    "sub_fields": [
                        {
                            "key": "field_64cb8b45e5fbf",
                            "label": "Content",
                            "name": "",
                            "aria-label": "",
                            "type": "tab",
                            "instructions": "",
                            "required": 0,
                            "conditional_logic": 0,
                            "wrapper": {
                                "width": "",
                                "class": "",
                                "id": ""
                            },
                            "placement": "top",
                            "endpoint": 0
                        },
                        {
                            "key": "field_64cb8b45e5fc0",
                            "label": "Pre Title",
                            "name": "pre_title",
                            "aria-label": "",
                            "type": "text",
                            "instructions": "",
                            "required": 0,
                            "conditional_logic": 0,
                            "wrapper": {
                                "width": "",
                                "class": "",
                                "id": ""
                            },
                            "default_value": "",
                            "maxlength": "",
                            "placeholder": "",
                            "prepend": "",
                            "append": ""
                        },
                        {
                            "key": "field_64cb8b7be5fcd",
                            "label": "Title",
                            "name": "title",
                            "aria-label": "",
                            "type": "text",
                            "instructions": "",
                            "required": 0,
                            "conditional_logic": 0,
                            "wrapper": {
                                "width": "",
                                "class": "",
                                "id": ""
                            },
                            "default_value": "",
                            "maxlength": "",
                            "placeholder": "",
                            "prepend": "",
                            "append": ""
                        },
                        {
                            "key": "field_64cb8b9ae5fce",
                            "label": "Button",
                            "name": "button",
                            "aria-label": "",
                            "type": "link",
                            "instructions": "",
                            "required": 0,
                            "conditional_logic": 0,
                            "wrapper": {
                                "width": "",
                                "class": "",
                                "id": ""
                            },
                            "return_format": "array"
                        },
                        {
                            "key": "field_64cb8b45e5fc1",
                            "label": "Cards",
                            "name": "cards",
                            "aria-label": "",
                            "type": "repeater",
                            "instructions": "",
                            "required": 0,
                            "conditional_logic": 0,
                            "wrapper": {
                                "width": "",
                                "class": "",
                                "id": ""
                            },
                            "layout": "block",
                            "min": 1,
                            "max": 0,
                            "collapsed": "field_64cb818282888",
                            "button_label": "Add Content",
                            "rows_per_page": 20,
                            "sub_fields": [
                                {
                                    "key": "field_64cb8c35e5fd0",
                                    "label": "Image",
                                    "name": "image",
                                    "aria-label": "",
                                    "type": "image",
                                    "instructions": "",
                                    "required": 1,
                                    "conditional_logic": 0,
                                    "wrapper": {
                                        "width": "",
                                        "class": "",
                                        "id": ""
                                    },
                                    "return_format": "id",
                                    "library": "all",
                                    "min_width": "",
                                    "min_height": "",
                                    "min_size": "",
                                    "max_width": "",
                                    "max_height": "",
                                    "max_size": "",
                                    "mime_types": "",
                                    "preview_size": "medium",
                                    "parent_repeater": "field_64cb8b45e5fc1"
                                },
                                {
                                    "key": "field_64cb8b45e5fc3",
                                    "label": "Title",
                                    "name": "title",
                                    "aria-label": "",
                                    "type": "link",
                                    "instructions": "",
                                    "required": 1,
                                    "conditional_logic": 0,
                                    "wrapper": {
                                        "width": "",
                                        "class": "",
                                        "id": ""
                                    },
                                    "return_format": "array",
                                    "parent_repeater": "field_64cb8b45e5fc1"
                                },
                                {
                                    "key": "field_64cb8c28e5fcf",
                                    "label": "Excerpt",
                                    "name": "excerpt",
                                    "aria-label": "",
                                    "type": "textarea",
                                    "instructions": "",
                                    "required": 0,
                                    "conditional_logic": 0,
                                    "wrapper": {
                                        "width": "",
                                        "class": "",
                                        "id": ""
                                    },
                                    "default_value": "",
                                    "maxlength": "",
                                    "rows": 4,
                                    "placeholder": "",
                                    "new_lines": "br",
                                    "parent_repeater": "field_64cb8b45e5fc1"
                                }
                            ]
                        },
                        {
                            "key": "field_64cb8b45e5fca",
                            "label": "Settings",
                            "name": "",
                            "aria-label": "",
                            "type": "tab",
                            "instructions": "",
                            "required": 0,
                            "conditional_logic": 0,
                            "wrapper": {
                                "width": "",
                                "class": "",
                                "id": ""
                            },
                            "placement": "top",
                            "endpoint": 0
                        },
                        {
                            "key": "field_64cb8b45e5fcb",
                            "label": "Section Classes",
                            "name": "section_classes",
                            "aria-label": "",
                            "type": "text",
                            "instructions": "Space separated section classes.",
                            "required": 0,
                            "conditional_logic": 0,
                            "wrapper": {
                                "width": "",
                                "class": "",
                                "id": ""
                            },
                            "default_value": "",
                            "maxlength": "",
                            "placeholder": "",
                            "prepend": "",
                            "append": ""
                        },
                        {
                            "key": "field_64cb8b45e5fcc",
                            "label": "Section ID",
                            "name": "section_id",
                            "aria-label": "",
                            "type": "text",
                            "instructions": "",
                            "required": 0,
                            "conditional_logic": 0,
                            "wrapper": {
                                "width": "",
                                "class": "",
                                "id": ""
                            },
                            "default_value": "",
                            "maxlength": "",
                            "placeholder": "",
                            "prepend": "",
                            "append": ""
                        }
                    ],
                    "min": "",
                    "max": ""
                },
                "layout_64cb931a68313": {
                    "key": "layout_64cb931a68313",
                    "name": "featured_blogs",
                    "label": "Featured Blogs",
                    "display": "block",
                    "sub_fields": [
                        {
                            "key": "field_64cb931a68314",
                            "label": "Content",
                            "name": "",
                            "aria-label": "",
                            "type": "tab",
                            "instructions": "",
                            "required": 0,
                            "conditional_logic": 0,
                            "wrapper": {
                                "width": "",
                                "class": "",
                                "id": ""
                            },
                            "placement": "top",
                            "endpoint": 0
                        },
                        {
                            "key": "field_64cb931a68316",
                            "label": "Title",
                            "name": "title",
                            "aria-label": "",
                            "type": "text",
                            "instructions": "",
                            "required": 0,
                            "conditional_logic": 0,
                            "wrapper": {
                                "width": "",
                                "class": "",
                                "id": ""
                            },
                            "default_value": "",
                            "maxlength": "",
                            "placeholder": "",
                            "prepend": "",
                            "append": ""
                        },
                        {
                            "key": "field_64cb931a68315",
                            "label": "Post Title",
                            "name": "post_title",
                            "aria-label": "",
                            "type": "text",
                            "instructions": "",
                            "required": 0,
                            "conditional_logic": 0,
                            "wrapper": {
                                "width": "",
                                "class": "",
                                "id": ""
                            },
                            "default_value": "",
                            "maxlength": "",
                            "placeholder": "",
                            "prepend": "",
                            "append": ""
                        },
                        {
                            "key": "field_64cb931a68317",
                            "label": "Button",
                            "name": "button",
                            "aria-label": "",
                            "type": "link",
                            "instructions": "",
                            "required": 0,
                            "conditional_logic": 0,
                            "wrapper": {
                                "width": "",
                                "class": "",
                                "id": ""
                            },
                            "return_format": "array"
                        },
                        {
                            "key": "field_64cb931a68318",
                            "label": "Posts",
                            "name": "posts",
                            "aria-label": "",
                            "type": "repeater",
                            "instructions": "",
                            "required": 0,
                            "conditional_logic": 0,
                            "wrapper": {
                                "width": "",
                                "class": "",
                                "id": ""
                            },
                            "layout": "block",
                            "min": 1,
                            "max": 0,
                            "collapsed": "field_64cb93306831f",
                            "button_label": "Add Post",
                            "rows_per_page": 20,
                            "sub_fields": [
                                {
                                    "key": "field_64cb93306831f",
                                    "label": "Select Post",
                                    "name": "select_post",
                                    "aria-label": "",
                                    "type": "post_object",
                                    "instructions": "",
                                    "required": 1,
                                    "conditional_logic": 0,
                                    "wrapper": {
                                        "width": "",
                                        "class": "",
                                        "id": ""
                                    },
                                    "post_type": [
                                        "post"
                                    ],
                                    "post_status": [
                                        "publish"
                                    ],
                                    "taxonomy": "",
                                    "return_format": "id",
                                    "multiple": 0,
                                    "allow_null": 0,
                                    "ui": 1,
                                    "parent_repeater": "field_64cb931a68318"
                                }
                            ]
                        },
                        {
                            "key": "field_64cb931a6831c",
                            "label": "Settings",
                            "name": "",
                            "aria-label": "",
                            "type": "tab",
                            "instructions": "",
                            "required": 0,
                            "conditional_logic": 0,
                            "wrapper": {
                                "width": "",
                                "class": "",
                                "id": ""
                            },
                            "placement": "top",
                            "endpoint": 0
                        },
                        {
                            "key": "field_64cb931a6831d",
                            "label": "Section Classes",
                            "name": "section_classes",
                            "aria-label": "",
                            "type": "text",
                            "instructions": "Space separated section classes.",
                            "required": 0,
                            "conditional_logic": 0,
                            "wrapper": {
                                "width": "",
                                "class": "",
                                "id": ""
                            },
                            "default_value": "",
                            "maxlength": "",
                            "placeholder": "",
                            "prepend": "",
                            "append": ""
                        },
                        {
                            "key": "field_64cb931a6831e",
                            "label": "Section ID",
                            "name": "section_id",
                            "aria-label": "",
                            "type": "text",
                            "instructions": "",
                            "required": 0,
                            "conditional_logic": 0,
                            "wrapper": {
                                "width": "",
                                "class": "",
                                "id": ""
                            },
                            "default_value": "",
                            "maxlength": "",
                            "placeholder": "",
                            "prepend": "",
                            "append": ""
                        }
                    ],
                    "min": "",
                    "max": ""
                },
                "layout_64cba3a72c07f": {
                    "key": "layout_64cba3a72c07f",
                    "name": "faqs",
                    "label": "FAQs",
                    "display": "block",
                    "sub_fields": [
                        {
                            "key": "field_64cba3a72c083",
                            "label": "Content",
                            "name": "",
                            "aria-label": "",
                            "type": "tab",
                            "instructions": "",
                            "required": 0,
                            "conditional_logic": 0,
                            "wrapper": {
                                "width": "",
                                "class": "",
                                "id": ""
                            },
                            "placement": "top",
                            "endpoint": 0
                        },
                        {
                            "key": "field_64cba3a72c084",
                            "label": "Title",
                            "name": "title",
                            "aria-label": "",
                            "type": "text",
                            "instructions": "",
                            "required": 0,
                            "conditional_logic": 0,
                            "wrapper": {
                                "width": "",
                                "class": "",
                                "id": ""
                            },
                            "default_value": "",
                            "maxlength": "",
                            "placeholder": "",
                            "prepend": "",
                            "append": ""
                        },
                        {
                            "key": "field_64cba3a72c087",
                            "label": "FAQs",
                            "name": "faqs",
                            "aria-label": "",
                            "type": "repeater",
                            "instructions": "",
                            "required": 0,
                            "conditional_logic": 0,
                            "wrapper": {
                                "width": "",
                                "class": "",
                                "id": ""
                            },
                            "layout": "block",
                            "min": 1,
                            "max": 0,
                            "collapsed": "field_64cb93306831f",
                            "button_label": "Add FAQ",
                            "rows_per_page": 20,
                            "sub_fields": [
                                {
                                    "key": "field_64cba3c12c08c",
                                    "label": "Question",
                                    "name": "question",
                                    "aria-label": "",
                                    "type": "text",
                                    "instructions": "",
                                    "required": 0,
                                    "conditional_logic": 0,
                                    "wrapper": {
                                        "width": "",
                                        "class": "",
                                        "id": ""
                                    },
                                    "default_value": "",
                                    "maxlength": "",
                                    "placeholder": "",
                                    "prepend": "",
                                    "append": "",
                                    "parent_repeater": "field_64cba3a72c087"
                                },
                                {
                                    "key": "field_64cba3cd2c08d",
                                    "label": "Answer",
                                    "name": "answer",
                                    "aria-label": "",
                                    "type": "textarea",
                                    "instructions": "",
                                    "required": 0,
                                    "conditional_logic": 0,
                                    "wrapper": {
                                        "width": "",
                                        "class": "",
                                        "id": ""
                                    },
                                    "default_value": "",
                                    "maxlength": "",
                                    "rows": 4,
                                    "placeholder": "",
                                    "new_lines": "br",
                                    "parent_repeater": "field_64cba3a72c087"
                                }
                            ]
                        },
                        {
                            "key": "field_64cba3a72c089",
                            "label": "Settings",
                            "name": "",
                            "aria-label": "",
                            "type": "tab",
                            "instructions": "",
                            "required": 0,
                            "conditional_logic": 0,
                            "wrapper": {
                                "width": "",
                                "class": "",
                                "id": ""
                            },
                            "placement": "top",
                            "endpoint": 0
                        },
                        {
                            "key": "field_64cba3a72c08a",
                            "label": "Section Classes",
                            "name": "section_classes",
                            "aria-label": "",
                            "type": "text",
                            "instructions": "Space separated section classes.",
                            "required": 0,
                            "conditional_logic": 0,
                            "wrapper": {
                                "width": "",
                                "class": "",
                                "id": ""
                            },
                            "default_value": "",
                            "maxlength": "",
                            "placeholder": "",
                            "prepend": "",
                            "append": ""
                        },
                        {
                            "key": "field_64cba3a72c08b",
                            "label": "Section ID",
                            "name": "section_id",
                            "aria-label": "",
                            "type": "text",
                            "instructions": "",
                            "required": 0,
                            "conditional_logic": 0,
                            "wrapper": {
                                "width": "",
                                "class": "",
                                "id": ""
                            },
                            "default_value": "",
                            "maxlength": "",
                            "placeholder": "",
                            "prepend": "",
                            "append": ""
                        }
                    ],
                    "min": "",
                    "max": ""
                },
                "layout_64cba59bd1c04": {
                    "key": "layout_64cba59bd1c04",
                    "name": "two_column_content",
                    "label": "Two Column Content",
                    "display": "block",
                    "sub_fields": [
                        {
                            "key": "field_64cba59bd1c05",
                            "label": "Content",
                            "name": "",
                            "aria-label": "",
                            "type": "tab",
                            "instructions": "",
                            "required": 0,
                            "conditional_logic": 0,
                            "wrapper": {
                                "width": "",
                                "class": "",
                                "id": ""
                            },
                            "placement": "top",
                            "endpoint": 0
                        },
                        {
                            "key": "field_64cba5cfd1c0e",
                            "label": "Image",
                            "name": "image",
                            "aria-label": "",
                            "type": "image",
                            "instructions": "",
                            "required": 1,
                            "conditional_logic": 0,
                            "wrapper": {
                                "width": "",
                                "class": "",
                                "id": ""
                            },
                            "return_format": "id",
                            "library": "all",
                            "min_width": "",
                            "min_height": "",
                            "min_size": "",
                            "max_width": "",
                            "max_height": "",
                            "max_size": "",
                            "mime_types": "",
                            "preview_size": "medium"
                        },
                        {
                            "key": "field_64cba59bd1c06",
                            "label": "Title",
                            "name": "title",
                            "aria-label": "",
                            "type": "text",
                            "instructions": "",
                            "required": 1,
                            "conditional_logic": 0,
                            "wrapper": {
                                "width": "",
                                "class": "",
                                "id": ""
                            },
                            "default_value": "",
                            "maxlength": "",
                            "placeholder": "",
                            "prepend": "",
                            "append": ""
                        },
                        {
                            "key": "field_64cba5b3d1c0d",
                            "label": "Description",
                            "name": "description",
                            "aria-label": "",
                            "type": "textarea",
                            "instructions": "",
                            "required": 0,
                            "conditional_logic": 0,
                            "wrapper": {
                                "width": "",
                                "class": "",
                                "id": ""
                            },
                            "default_value": "",
                            "maxlength": "",
                            "rows": 4,
                            "placeholder": "",
                            "new_lines": "br"
                        },
                        {
                            "key": "field_64cbec4c1ded9",
                            "label": "Form",
                            "name": "form",
                            "aria-label": "",
                            "type": "post_object",
                            "instructions": "",
                            "required": 0,
                            "conditional_logic": 0,
                            "wrapper": {
                                "width": "",
                                "class": "",
                                "id": ""
                            },
                            "post_type": [
                                "wpforms"
                            ],
                            "post_status": "",
                            "taxonomy": "",
                            "return_format": "id",
                            "multiple": 0,
                            "allow_null": 0,
                            "ui": 1
                        },
                        {
                            "key": "field_64cba59bd1c0a",
                            "label": "Settings",
                            "name": "",
                            "aria-label": "",
                            "type": "tab",
                            "instructions": "",
                            "required": 0,
                            "conditional_logic": 0,
                            "wrapper": {
                                "width": "",
                                "class": "",
                                "id": ""
                            },
                            "placement": "top",
                            "endpoint": 0
                        },
                        {
                            "key": "field_64cba59bd1c0b",
                            "label": "Section Classes",
                            "name": "section_classes",
                            "aria-label": "",
                            "type": "text",
                            "instructions": "Space separated section classes.",
                            "required": 0,
                            "conditional_logic": 0,
                            "wrapper": {
                                "width": "",
                                "class": "",
                                "id": ""
                            },
                            "default_value": "",
                            "maxlength": "",
                            "placeholder": "",
                            "prepend": "",
                            "append": ""
                        },
                        {
                            "key": "field_64cba59bd1c0c",
                            "label": "Section ID",
                            "name": "section_id",
                            "aria-label": "",
                            "type": "text",
                            "instructions": "",
                            "required": 0,
                            "conditional_logic": 0,
                            "wrapper": {
                                "width": "",
                                "class": "",
                                "id": ""
                            },
                            "default_value": "",
                            "maxlength": "",
                            "placeholder": "",
                            "prepend": "",
                            "append": ""
                        }
                    ],
                    "min": "",
                    "max": ""
                },
                "layout_64cba7abadc90": {
                    "key": "layout_64cba7abadc90",
                    "name": "cta",
                    "label": "CTA",
                    "display": "block",
                    "sub_fields": [
                        {
                            "key": "field_64cba7abadc91",
                            "label": "Content",
                            "name": "",
                            "aria-label": "",
                            "type": "tab",
                            "instructions": "",
                            "required": 0,
                            "conditional_logic": 0,
                            "wrapper": {
                                "width": "",
                                "class": "",
                                "id": ""
                            },
                            "placement": "top",
                            "endpoint": 0
                        },
                        {
                            "key": "field_64cba7abadc92",
                            "label": "Image",
                            "name": "image",
                            "aria-label": "",
                            "type": "image",
                            "instructions": "",
                            "required": 1,
                            "conditional_logic": 0,
                            "wrapper": {
                                "width": "",
                                "class": "",
                                "id": ""
                            },
                            "return_format": "id",
                            "library": "all",
                            "min_width": "",
                            "min_height": "",
                            "min_size": "",
                            "max_width": "",
                            "max_height": "",
                            "max_size": "",
                            "mime_types": "",
                            "preview_size": "medium"
                        },
                        {
                            "key": "field_64cba7abadc93",
                            "label": "Title",
                            "name": "title",
                            "aria-label": "",
                            "type": "text",
                            "instructions": "",
                            "required": 1,
                            "conditional_logic": 0,
                            "wrapper": {
                                "width": "",
                                "class": "",
                                "id": ""
                            },
                            "default_value": "",
                            "maxlength": "",
                            "placeholder": "",
                            "prepend": "",
                            "append": ""
                        },
                        {
                            "key": "field_64cba7abadc94",
                            "label": "Phone",
                            "name": "phone",
                            "aria-label": "",
                            "type": "text",
                            "instructions": "",
                            "required": 0,
                            "conditional_logic": 0,
                            "wrapper": {
                                "width": "",
                                "class": "",
                                "id": ""
                            },
                            "default_value": "",
                            "maxlength": "",
                            "placeholder": "",
                            "prepend": "",
                            "append": ""
                        },
                        {
                            "key": "field_64cba7cbadc98",
                            "label": "Social Title",
                            "name": "social_title",
                            "aria-label": "",
                            "type": "text",
                            "instructions": "",
                            "required": 0,
                            "conditional_logic": 0,
                            "wrapper": {
                                "width": "",
                                "class": "",
                                "id": ""
                            },
                            "default_value": "",
                            "maxlength": "",
                            "placeholder": "",
                            "prepend": "",
                            "append": ""
                        },
                        {
                            "key": "field_64cba7abadc95",
                            "label": "Settings",
                            "name": "",
                            "aria-label": "",
                            "type": "tab",
                            "instructions": "",
                            "required": 0,
                            "conditional_logic": 0,
                            "wrapper": {
                                "width": "",
                                "class": "",
                                "id": ""
                            },
                            "placement": "top",
                            "endpoint": 0
                        },
                        {
                            "key": "field_64cba7abadc96",
                            "label": "Section Classes",
                            "name": "section_classes",
                            "aria-label": "",
                            "type": "text",
                            "instructions": "Space separated section classes.",
                            "required": 0,
                            "conditional_logic": 0,
                            "wrapper": {
                                "width": "",
                                "class": "",
                                "id": ""
                            },
                            "default_value": "",
                            "maxlength": "",
                            "placeholder": "",
                            "prepend": "",
                            "append": ""
                        },
                        {
                            "key": "field_64cba7abadc97",
                            "label": "Section ID",
                            "name": "section_id",
                            "aria-label": "",
                            "type": "text",
                            "instructions": "",
                            "required": 0,
                            "conditional_logic": 0,
                            "wrapper": {
                                "width": "",
                                "class": "",
                                "id": ""
                            },
                            "default_value": "",
                            "maxlength": "",
                            "placeholder": "",
                            "prepend": "",
                            "append": ""
                        }
                    ],
                    "min": "",
                    "max": ""
                }
            },
            "min": "",
            "max": "",
            "button_label": "Add Block"
        }
    ],
    "location": [
        [
            {
                "param": "post_template",
                "operator": "==",
                "value": "page-templates\/page-composer.php"
            }
        ]
    ],
    "menu_order": 0,
    "position": "acf_after_title",
    "style": "default",
    "label_placement": "top",
    "instruction_placement": "label",
    "hide_on_screen": [
        "the_content",
        "discussion",
        "comments"
    ],
    "active": true,
    "description": "",
    "show_in_rest": 0,
    "modified": 1691086179
}
